methodfinder/__init__.py
methodfinder/methodfinder-test.py
methodfinder/methodfinder.py
methodfinder-0.0.3.dist-info/LICENSE.txt
methodfinder-0.0.3.dist-info/METADATA
methodfinder-0.0.3.dist-info/WHEEL
methodfinder-0.0.3.dist-info/top_level.txt
methodfinder-0.0.3.dist-info/RECORD
